MANIFEST.in
README.txt
setup.cfg
setup.py
docs/HISTORY.txt
horae/__init__.py
horae.search.egg-info/PKG-INFO
horae.search.egg-info/SOURCES.txt
horae.search.egg-info/dependency_links.txt
horae.search.egg-info/entry_points.txt
horae.search.egg-info/namespace_packages.txt
horae.search.egg-info/not-zip-safe
horae.search.egg-info/requires.txt
horae.search.egg-info/top_level.txt
horae/search/__init__.py
horae/search/catalog.py
horae/search/configure.zcml
horae/search/interfaces.py
horae/search/properties.py
horae/search/search.py
horae/search/traversal.py
horae/search/upgrade.py
horae/search/utils.py
horae/search/viewlets.py
horae/search/vocabulary.py
horae/search/locales/horae.search.pot
horae/search/locales/de/LC_MESSAGES/horae.search.mo
horae/search/locales/de/LC_MESSAGES/horae.search.po